fredx/__init__.py
fredx/main.py
fredx-0.0.5.dist-info/LICENSE
fredx-0.0.5.dist-info/METADATA
fredx-0.0.5.dist-info/WHEEL
fredx-0.0.5.dist-info/top_level.txt
fredx-0.0.5.dist-info/RECORD
