Metadata-Version: 2.1
Name: fredx
Version: 0.0.5
Summary: St. Louis Federal Reserve FRED API
Home-page: https://github.com/AhmedThahir/fredx
Author: Ahmed Thahir
Author-email: ahmedthahir2002@gmail.com
License: MIT
Keywords: fred,api,federal reserve,st. louis fed,async
Classifier: Development Status :: 1 - Planning
Classifier: Intended Audience :: Developers
Classifier: Programming Language :: Python :: 3
Classifier: Operating System :: Unix
Classifier: Operating System :: MacOS :: MacOS X
Classifier: Operating System :: Microsoft :: Windows
Classifier: Topic :: Internet
Classifier: Topic :: Internet :: WWW/HTTP
Classifier: Natural Language :: English
License-File: LICENSE
Requires-Dist: aiolimiter
Requires-Dist: httpx[http2]
Requires-Dist: numpy
Requires-Dist: pandas
